odoo/addons/sale_force_invoiced_quantity/README.rst
odoo/addons/sale_force_invoiced_quantity/__init__.py
odoo/addons/sale_force_invoiced_quantity/__manifest__.py
odoo/addons/sale_force_invoiced_quantity/demo/demo_product.xml
odoo/addons/sale_force_invoiced_quantity/demo/demo_sale_order.xml
odoo/addons/sale_force_invoiced_quantity/i18n/it.po
odoo/addons/sale_force_invoiced_quantity/i18n/sale_force_invoiced_quantity.pot
odoo/addons/sale_force_invoiced_quantity/models/__init__.py
odoo/addons/sale_force_invoiced_quantity/models/sale_order_line.py
odoo/addons/sale_force_invoiced_quantity/readme/CONFIGURE.md
odoo/addons/sale_force_invoiced_quantity/readme/CONTEXT.md
odoo/addons/sale_force_invoiced_quantity/readme/CONTRIBUTORS.md
odoo/addons/sale_force_invoiced_quantity/readme/DESCRIPTION.md
odoo/addons/sale_force_invoiced_quantity/readme/USAGE.md
odoo/addons/sale_force_invoiced_quantity/static/description/icon.png
odoo/addons/sale_force_invoiced_quantity/static/description/index.html
odoo/addons/sale_force_invoiced_quantity/tests/__init__.py
odoo/addons/sale_force_invoiced_quantity/tests/test_sale_force_invoiced_qty.py
odoo/addons/sale_force_invoiced_quantity/views/sale_order.xml
odoo_addon_sale_force_invoiced_quantity-17.0.1.0.0.2.dist-info/METADATA
odoo_addon_sale_force_invoiced_quantity-17.0.1.0.0.2.dist-info/WHEEL
odoo_addon_sale_force_invoiced_quantity-17.0.1.0.0.2.dist-info/top_level.txt
odoo_addon_sale_force_invoiced_quantity-17.0.1.0.0.2.dist-info/RECORD
